walletpay/Exception.py
walletpay/Order.py
walletpay/WalletPayAPI.py
walletpay/__init__.py
wallet_pay-0.1.dist-info/LICENSE
wallet_pay-0.1.dist-info/METADATA
wallet_pay-0.1.dist-info/WHEEL
wallet_pay-0.1.dist-info/top_level.txt
wallet_pay-0.1.dist-info/RECORD
