Metadata-Version: 2.1
Name: wallet-pay
Version: 0.1
Summary: A Python client for the pay.wallet.tg API
Author: Max Palehin
Author-email: maksim.wsem@gmail.com
License: MIT
Keywords: WalletPay API Client
License-File: LICENSE
Requires-Dist: requests
